MANIFEST.in
README.rst
setup.py
splinter/__init__.py
splinter/browser.py
splinter/cookie_manager.py
splinter/element_list.py
splinter/exceptions.py
splinter/meta.py
splinter/utils.py
splinter/driver/__init__.py
splinter/driver/djangoclient.py
splinter/driver/element_present.py
splinter/driver/flaskclient.py
splinter/driver/lxmldriver.py
splinter/driver/zopetestbrowser.py
splinter/driver/webdriver/__init__.py
splinter/driver/webdriver/chrome.py
splinter/driver/webdriver/cookie_manager.py
splinter/driver/webdriver/firefox.py
splinter/driver/webdriver/phantomjs.py
splinter/driver/webdriver/remote.py
splinter/request_handler/__init__.py
splinter/request_handler/status_code.py
wood_splinter.egg-info/PKG-INFO
wood_splinter.egg-info/SOURCES.txt
wood_splinter.egg-info/dependency_links.txt
wood_splinter.egg-info/requires.txt
wood_splinter.egg-info/top_level.txt