Metadata-Version: 1.1
Name: wood-splinter
Version: 0.7.4.1
Summary: browser abstraction for web acceptance testing
Home-page: https://github.com/MihaiBalint/splinter
Author: MihaiBalint
Author-email: balint.mihai@gmail.com
License: UNKNOWN
Platform: UNKNOWN
Classifier: Programming Language :: Python :: 2
Classifier: Programming Language :: Python :: 3
Classifier: Programming Language :: Python :: 2.6
Classifier: Programming Language :: Python :: 2.7
Classifier: Programming Language :: Python :: 3.3
Classifier: Programming Language :: Python :: 3.4
